annembed_rs-0.1.0.dist-info/METADATA
annembed_rs-0.1.0.dist-info/WHEEL
annembed_rs-0.1.0.dist-info/licenses/LICENSE-APACHE
annembed_rs-0.1.0.dist-info/licenses/LICENSE-MIT
annembed/__init__.py
annembed/annembed.cpython-310-darwin.so
annembed_rs-0.1.0.dist-info/RECORD
