Metadata-Version: 2.4
Name: annembed_rs
Version: 0.1.0
License-File: LICENSE-APACHE
License-File: LICENSE-MIT
Summary: Python bindings for the annembed Rust crate
Keywords: algorithms,ann,embedding,dimension-reduction,umap
Author: jeanpierre.both@gmail.com
Author-email: Jianshu Zhao <jianshuzhao@yahoo.com>
License: MIT
Requires-Python: >=3.9
Project-URL: Source Code, https://github.com/jean-pierreBoth/annembed
